README.rst
setup.py
django_multiple_domains.egg-info/PKG-INFO
django_multiple_domains.egg-info/SOURCES.txt
django_multiple_domains.egg-info/dependency_links.txt
django_multiple_domains.egg-info/top_level.txt
multipledomain/__init__.py
multipledomain/middleware.py