Metadata-Version: 1.1
Name: django-multiple-domains
Version: 0.0.1
Summary: Django middleware for serving single Django instance in multiple domains with different urls.
Home-page: https://github.com/qlio/django-multiple-domains
Author: Bulgantamir Gankhuyag
Author-email: mr.unagaldai@gmail.com
License: UNKNOWN
Keywords: django url domain host multi
Platform: UNKNOWN
Classifier: Development Status :: 4 - Beta
Classifier: Environment :: Web Environment
Classifier: Framework :: Django
Classifier: Intended Audience :: Developers
Classifier: Operating System :: OS Independent
Classifier: Programming Language :: Python
Classifier: Programming Language :: Python :: 2.7
Classifier: Programming Language :: Python :: 3.5
Classifier: Topic :: Internet :: WWW/HTTP
Classifier: Topic :: Internet :: WWW/HTTP :: Dynamic Content
Classifier: Topic :: Internet :: WWW/HTTP :: WSGI
Classifier: Topic :: Software Development :: Libraries :: Application Frameworks
Classifier: Topic :: Software Development :: Libraries :: Python Modules
